deeptech/__init__.py
deeptech/core/__init__.py
deeptech/core/annotations.py
deeptech/core/checkpoint.py
deeptech/core/cli.py
deeptech/core/cli_tools.py
deeptech/core/config.py
deeptech/core/definitions.py
deeptech/core/logging.py
deeptech/data/__init__.py
deeptech/data/dataloader_keras.py
deeptech/data/dataloader_pytorch.py
deeptech/data/dataset.py
deeptech/data/transformer.py
deeptech/data/datasets/__init__.py
deeptech/data/datasets/casia_faces_dataset.py
deeptech/data/datasets/coco_dataset.py
deeptech/data/datasets/fashion_mnist_dataset.py
deeptech/data/datasets/images_in_classfolders_dataset.py
deeptech/data/transformers/__init__.py
deeptech/data/visualizations/__init__.py
deeptech/data/visualizations/plot_boxes.py
deeptech/examples/__init__.py
deeptech/examples/coco_faster_rcnn.py
deeptech/examples/mnist_custom_dataset.py
deeptech/examples/mnist_custom_loss.py
deeptech/examples/mnist_custom_model.py
deeptech/examples/mnist_simple.py
deeptech/model/__init__.py
deeptech/model/module_from_json.py
deeptech/model/module_registry.py
deeptech/model/layers/__init__.py
deeptech/model/layers/activation.py
deeptech/model/layers/batch_normalization.py
deeptech/model/layers/convolution.py
deeptech/model/layers/dense.py
deeptech/model/layers/detection.py
deeptech/model/layers/flatten.py
deeptech/model/layers/image_conversion.py
deeptech/model/layers/pooling.py
deeptech/model/layers/reshape.py
deeptech/model/layers/roi_ops.py
deeptech/model/layers/selection.py
deeptech/model/layers/sequential.py
deeptech/model/layers/tensor_combiners.py
deeptech/model/models/__init__.py
deeptech/model/models/imagenet.py
deeptech/training/__init__.py
deeptech/training/tensorboard.py
deeptech/training/callbacks/__init__.py
deeptech/training/callbacks/base_callback.py
deeptech/training/callbacks/checkpoint_callback.py
deeptech/training/callbacks/log_callback.py
deeptech/training/callbacks/tensorboard_callback.py
deeptech/training/losses/__init__.py
deeptech/training/losses/classification.py
deeptech-20210210.dist-info/LICENSE
deeptech-20210210.dist-info/METADATA
deeptech-20210210.dist-info/WHEEL
deeptech-20210210.dist-info/entry_points.txt
deeptech-20210210.dist-info/top_level.txt
deeptech-20210210.dist-info/RECORD
