Metadata-Version: 2.1
Name: deeptech
Version: 20210210
Summary: A library to help writing ai functions with ease.
Home-page: https://github.com/penguinmenac3/deeptech
Author: Michael Fuerst
Author-email: mail@michaelfuerst.de
License: MIT
Download-URL: https://github.com/penguinmenac3/deeptech/tarball/20210210
Platform: UNKNOWN
Classifier: Development Status :: 3 - Alpha
Classifier: Intended Audience :: Developers
Classifier: Programming Language :: Python
Requires-Dist: numpy
Requires-Dist: imageio
Requires-Dist: jstyleson
Requires-Dist: torch
Requires-Dist: torchvision
Requires-Dist: GPUtil
Provides-Extra: all
Requires-Dist: open3d (==0.9.0.0) ; extra == 'all'
Requires-Dist: tensorboard ; extra == 'all'
Requires-Dist: nose2 ; extra == 'all'
Requires-Dist: packaging ; extra == 'all'
Provides-Extra: dev
Requires-Dist: nose2 ; extra == 'dev'
Requires-Dist: packaging ; extra == 'dev'
Provides-Extra: visualization
Requires-Dist: open3d (==0.9.0.0) ; extra == 'visualization'
Requires-Dist: tensorboard ; extra == 'visualization'
